projmap/__init__.py
projmap/basemap.py
projmap/cartomap.py
projmap/config.py
projmap/data/pf.txt
projmap/data/saccf.txt
projmap/data/saf.txt
projmap/data/sbdy.txt
projmap/data/stf.txt
projmap/map_region.py
projmap/map_regions.cfg
projmap-0.89.dist-info/WHEEL
projmap-0.89.dist-info/METADATA
projmap-0.89.dist-info/RECORD
