Metadata-Version: 2.1
Name: projmap
Version: 0.89
Summary: High level wrapper of matplotlibs mapping package
Author: Bror Jonsson
Author-email: brorfred@gmail.com
Requires-Python: >=3.6,<4.0
Classifier: Programming Language :: Python :: 3
Classifier: Programming Language :: Python :: 3.6
Classifier: Programming Language :: Python :: 3.7
Classifier: Programming Language :: Python :: 3.8
Requires-Dist: cartopy (>=0.18.0)
Requires-Dist: cython (>=0.29.21,<0.30.0)
Requires-Dist: matplotlib (>=3.0,<4.0)
Requires-Dist: numpy (>=1.15,<2.0)
Requires-Dist: pyshp (>=2.1.0,<3.0.0)
Requires-Dist: scipy (>=1.3,<2.0)
Requires-Dist: six (>=1.12,<2.0)
